[{"txt":"南昌市","val":"159","par":null,"list":[{"txt":"东湖区","val":"1552","par":null,"list":null},{"txt":"西湖区","val":"1553","par":null,"list":null},{"txt":"青云谱区","val":"1554","par":null,"list":null},{"txt":"湾里区","val":"1555","par":null,"list":null},{"txt":"青山湖区","val":"1556","par":null,"list":null},{"txt":"南昌县","val":"1557","par":null,"list":null},{"txt":"新建县","val":"1558","par":null,"list":null},{"txt":"安义县","val":"1559","par":null,"list":null},{"txt":"进贤县","val":"1560","par":null,"list":null},{"txt":"经济技术开发区","val":"1561","par":null,"list":null},{"txt":"红谷滩新区","val":"1562","par":null,"list":null},{"txt":"高新技术产业开发区","val":"1563","par":null,"list":null},{"txt":"桑海经济技术开发区","val":"1564","par":null,"list":null},{"txt":"英雄经济开发区","val":"1565","par":null,"list":null}]},{"txt":"景德镇市","val":"160","par":null,"list":[{"txt":"昌江区","val":"1566","par":null,"list":null},{"txt":"珠山区","val":"1567","par":null,"list":null},{"txt":"浮梁县","val":"1568","par":null,"list":null},{"txt":"乐平市","val":"1569","par":null,"list":null}]},{"txt":"萍乡市","val":"161","par":null,"list":[{"txt":"安源区","val":"1570","par":null,"list":null},{"txt":"湘东区","val":"1571","par":null,"list":null},{"txt":"莲花县","val":"1572","par":null,"list":null},{"txt":"上栗县","val":"1573","par":null,"list":null},{"txt":"芦溪县","val":"1574","par":null,"list":null}]},{"txt":"九江市","val":"162","par":null,"list":[{"txt":"庐山区","val":"1575","par":null,"list":null},{"txt":"浔阳区","val":"1576","par":null,"list":null},{"txt":"九江县","val":"1577","par":null,"list":null},{"txt":"武宁县","val":"1578","par":null,"list":null},{"txt":"修水县","val":"1579","par":null,"list":null},{"txt":"永修县","val":"1580","par":null,"list":null},{"txt":"德安县","val":"1581","par":null,"list":null},{"txt":"星子县","val":"1582","par":null,"list":null},{"txt":"都昌县","val":"1583","par":null,"list":null},{"txt":"湖口县","val":"1584","par":null,"list":null},{"txt":"彭泽县","val":"1585","par":null,"list":null},{"txt":"瑞昌市","val":"1586","par":null,"list":null},{"txt":"共青城市","val":"3380","par":null,"list":null},{"txt":"九江经济技术开发区","val":"7605","par":null,"list":null}]},{"txt":"新余市","val":"163","par":null,"list":[{"txt":"渝水区","val":"1587","par":null,"list":null},{"txt":"分宜县","val":"1588","par":null,"list":null}]},{"txt":"鹰潭市","val":"164","par":null,"list":[{"txt":"月湖区","val":"1589","par":null,"list":null},{"txt":"余江县","val":"1590","par":null,"list":null},{"txt":"贵溪市","val":"1591","par":null,"list":null}]},{"txt":"赣州市","val":"165","par":null,"list":[{"txt":"章贡区","val":"1592","par":null,"list":null},{"txt":"赣县","val":"1593","par":null,"list":null},{"txt":"信丰县","val":"1594","par":null,"list":null},{"txt":"大余县","val":"1595","par":null,"list":null},{"txt":"上犹县","val":"1596","par":null,"list":null},{"txt":"崇义县","val":"1597","par":null,"list":null},{"txt":"安远县","val":"1598","par":null,"list":null},{"txt":"龙南县","val":"1599","par":null,"list":null},{"txt":"定南县","val":"1600","par":null,"list":null},{"txt":"全南县","val":"1601","par":null,"list":null},{"txt":"宁都县","val":"1602","par":null,"list":null},{"txt":"于都县","val":"1603","par":null,"list":null},{"txt":"兴国县","val":"1604","par":null,"list":null},{"txt":"会昌县","val":"1605","par":null,"list":null},{"txt":"寻乌县","val":"1606","par":null,"list":null},{"txt":"石城县","val":"1607","par":null,"list":null},{"txt":"瑞金市","val":"1608","par":null,"list":null},{"txt":"南康市","val":"1609","par":null,"list":null}]},{"txt":"吉安市","val":"166","par":null,"list":[{"txt":"吉州区","val":"1610","par":null,"list":null},{"txt":"青原区","val":"1611","par":null,"list":null},{"txt":"吉安县","val":"1612","par":null,"list":null},{"txt":"吉水县","val":"1613","par":null,"list":null},{"txt":"峡江县","val":"1614","par":null,"list":null},{"txt":"新干县","val":"1615","par":null,"list":null},{"txt":"永丰县","val":"1616","par":null,"list":null},{"txt":"泰和县","val":"1617","par":null,"list":null},{"txt":"遂川县","val":"1618","par":null,"list":null},{"txt":"万安县","val":"1619","par":null,"list":null},{"txt":"安福县","val":"1620","par":null,"list":null},{"txt":"永新县","val":"1621","par":null,"list":null},{"txt":"井冈山市","val":"1622","par":null,"list":null}]},{"txt":"宜春市","val":"167","par":null,"list":[{"txt":"袁州区","val":"1623","par":null,"list":null},{"txt":"奉新县","val":"1624","par":null,"list":null},{"txt":"万载县","val":"1625","par":null,"list":null},{"txt":"上高县","val":"1626","par":null,"list":null},{"txt":"宜丰县","val":"1627","par":null,"list":null},{"txt":"靖安县","val":"1628","par":null,"list":null},{"txt":"铜鼓县","val":"1629","par":null,"list":null},{"txt":"丰城市","val":"1630","par":null,"list":null},{"txt":"樟树市","val":"1631","par":null,"list":null},{"txt":"高安市","val":"1632","par":null,"list":null}]},{"txt":"抚州市","val":"168","par":null,"list":[{"txt":"临川区","val":"1633","par":null,"list":null},{"txt":"南城县","val":"1634","par":null,"list":null},{"txt":"黎川县","val":"1635","par":null,"list":null},{"txt":"南丰县","val":"1636","par":null,"list":null},{"txt":"崇仁县","val":"1637","par":null,"list":null},{"txt":"乐安县","val":"1638","par":null,"list":null},{"txt":"宜黄县","val":"1639","par":null,"list":null},{"txt":"金溪县","val":"1640","par":null,"list":null},{"txt":"资溪县","val":"1641","par":null,"list":null},{"txt":"东乡县","val":"1642","par":null,"list":null},{"txt":"广昌县","val":"1643","par":null,"list":null}]},{"txt":"上饶市","val":"169","par":null,"list":[{"txt":"信州区","val":"1644","par":null,"list":null},{"txt":"上饶县","val":"1645","par":null,"list":null},{"txt":"广丰县","val":"1646","par":null,"list":null},{"txt":"玉山县","val":"1647","par":null,"list":null},{"txt":"铅山县","val":"1648","par":null,"list":null},{"txt":"横峰县","val":"1649","par":null,"list":null},{"txt":"弋阳县","val":"1650","par":null,"list":null},{"txt":"余干县","val":"1651","par":null,"list":null},{"txt":"鄱阳县","val":"1652","par":null,"list":null},{"txt":"万年县","val":"1653","par":null,"list":null},{"txt":"婺源县","val":"1654","par":null,"list":null},{"txt":"德兴市","val":"1655","par":null,"list":null}]}]