[{"txt":"西安市","val":"325","par":null,"list":[{"txt":"新城区","val":"3019","par":null,"list":null},{"txt":"碑林区","val":"3020","par":null,"list":null},{"txt":"莲湖区","val":"3021","par":null,"list":null},{"txt":"灞桥区","val":"3022","par":null,"list":null},{"txt":"未央区","val":"3023","par":null,"list":null},{"txt":"雁塔区","val":"3024","par":null,"list":null},{"txt":"阎良区","val":"3025","par":null,"list":null},{"txt":"临潼区","val":"3026","par":null,"list":null},{"txt":"长安区","val":"3027","par":null,"list":null},{"txt":"蓝田县","val":"3028","par":null,"list":null},{"txt":"周至县","val":"3029","par":null,"list":null},{"txt":"户县","val":"3030","par":null,"list":null},{"txt":"高陵县","val":"3031","par":null,"list":null},{"txt":"高新区","val":"3032","par":null,"list":null}]},{"txt":"铜川市","val":"326","par":null,"list":[{"txt":"王益区","val":"3033","par":null,"list":null},{"txt":"印台区","val":"3034","par":null,"list":null},{"txt":"耀州区","val":"3035","par":null,"list":null},{"txt":"宜君县","val":"3036","par":null,"list":null},{"txt":"新区","val":"3037","par":null,"list":null}]},{"txt":"宝鸡市","val":"327","par":null,"list":[{"txt":"渭滨区","val":"3038","par":null,"list":null},{"txt":"金台区","val":"3039","par":null,"list":null},{"txt":"陈仓区","val":"3040","par":null,"list":null},{"txt":"凤翔县","val":"3041","par":null,"list":null},{"txt":"岐山县","val":"3042","par":null,"list":null},{"txt":"扶风县","val":"3043","par":null,"list":null},{"txt":"眉县","val":"3044","par":null,"list":null},{"txt":"陇县","val":"3045","par":null,"list":null},{"txt":"千阳县","val":"3046","par":null,"list":null},{"txt":"麟游县","val":"3047","par":null,"list":null},{"txt":"凤县","val":"3048","par":null,"list":null},{"txt":"太白县","val":"3049","par":null,"list":null}]},{"txt":"咸阳市","val":"328","par":null,"list":[{"txt":"秦都区","val":"3050","par":null,"list":null},{"txt":"渭城区","val":"3051","par":null,"list":null},{"txt":"杨陵区","val":"3052","par":null,"list":null},{"txt":"三原县","val":"3053","par":null,"list":null},{"txt":"泾阳县","val":"3054","par":null,"list":null},{"txt":"兴平市","val":"3055","par":null,"list":null},{"txt":"乾县","val":"3056","par":null,"list":null},{"txt":"礼泉县","val":"3057","par":null,"list":null},{"txt":"永寿县","val":"3058","par":null,"list":null},{"txt":"彬县","val":"3059","par":null,"list":null},{"txt":"长武县","val":"3060","par":null,"list":null},{"txt":"旬邑县","val":"3061","par":null,"list":null},{"txt":"淳化县","val":"3062","par":null,"list":null},{"txt":"武功县","val":"3063","par":null,"list":null}]},{"txt":"渭南市","val":"329","par":null,"list":[{"txt":"临渭区","val":"3064","par":null,"list":null},{"txt":"华县","val":"3065","par":null,"list":null},{"txt":"潼关县","val":"3066","par":null,"list":null},{"txt":"大荔县","val":"3067","par":null,"list":null},{"txt":"合阳县","val":"3068","par":null,"list":null},{"txt":"澄城县","val":"3069","par":null,"list":null},{"txt":"蒲城县","val":"3070","par":null,"list":null},{"txt":"白水县","val":"3071","par":null,"list":null},{"txt":"富平县","val":"3072","par":null,"list":null},{"txt":"韩城市","val":"3073","par":null,"list":null},{"txt":"华阴市","val":"3074","par":null,"list":null}]},{"txt":"延安市","val":"330","par":null,"list":[{"txt":"宝塔区","val":"3075","par":null,"list":null},{"txt":"延长县","val":"3076","par":null,"list":null},{"txt":"延川县","val":"3077","par":null,"list":null},{"txt":"子长县","val":"3078","par":null,"list":null},{"txt":"安塞县","val":"3079","par":null,"list":null},{"txt":"志丹县","val":"3080","par":null,"list":null},{"txt":"吴起县","val":"3081","par":null,"list":null},{"txt":"甘泉县","val":"3082","par":null,"list":null},{"txt":"富县","val":"3083","par":null,"list":null},{"txt":"洛川县","val":"3084","par":null,"list":null},{"txt":"宜川县","val":"3085","par":null,"list":null},{"txt":"黄龙县","val":"3086","par":null,"list":null},{"txt":"黄陵县","val":"3087","par":null,"list":null}]},{"txt":"汉中市","val":"331","par":null,"list":[{"txt":"汉台区","val":"3088","par":null,"list":null},{"txt":"南郑县","val":"3089","par":null,"list":null},{"txt":"城固县","val":"3090","par":null,"list":null},{"txt":"洋县","val":"3091","par":null,"list":null},{"txt":"西乡县","val":"3092","par":null,"list":null},{"txt":"勉县","val":"3093","par":null,"list":null},{"txt":"宁强县","val":"3094","par":null,"list":null},{"txt":"略阳县","val":"3095","par":null,"list":null},{"txt":"镇巴县","val":"3096","par":null,"list":null},{"txt":"留坝县","val":"3097","par":null,"list":null},{"txt":"佛坪县","val":"3098","par":null,"list":null},{"txt":"经济开发区","val":"3099","par":null,"list":null}]},{"txt":"榆林市","val":"332","par":null,"list":[{"txt":"榆阳区","val":"3100","par":null,"list":null},{"txt":"神木县","val":"3101","par":null,"list":null},{"txt":"府谷县","val":"3102","par":null,"list":null},{"txt":"横山县","val":"3103","par":null,"list":null},{"txt":"靖边县","val":"3104","par":null,"list":null},{"txt":"定边县","val":"3105","par":null,"list":null},{"txt":"绥德县","val":"3106","par":null,"list":null},{"txt":"米脂县","val":"3107","par":null,"list":null},{"txt":"佳县","val":"3108","par":null,"list":null},{"txt":"吴堡县","val":"3109","par":null,"list":null},{"txt":"清涧县","val":"3110","par":null,"list":null},{"txt":"子洲县","val":"3111","par":null,"list":null}]},{"txt":"安康市","val":"333","par":null,"list":[{"txt":"汉滨区","val":"3112","par":null,"list":null},{"txt":"汉阴县","val":"3113","par":null,"list":null},{"txt":"石泉县","val":"3114","par":null,"list":null},{"txt":"宁陕县","val":"3115","par":null,"list":null},{"txt":"紫阳县","val":"3116","par":null,"list":null},{"txt":"岚皋县","val":"3117","par":null,"list":null},{"txt":"平利县","val":"3118","par":null,"list":null},{"txt":"镇坪县","val":"3119","par":null,"list":null},{"txt":"旬阳县","val":"3120","par":null,"list":null},{"txt":"白河县","val":"3121","par":null,"list":null}]},{"txt":"商洛市","val":"334","par":null,"list":[{"txt":"商州区","val":"3122","par":null,"list":null},{"txt":"洛南县","val":"3123","par":null,"list":null},{"txt":"丹凤县","val":"3124","par":null,"list":null},{"txt":"商南县","val":"3125","par":null,"list":null},{"txt":"山阳县","val":"3126","par":null,"list":null},{"txt":"镇安县","val":"3127","par":null,"list":null},{"txt":"柞水县","val":"3128","par":null,"list":null}]}]